converso_ai/__init__.py
converso_ai-1.0.7.dist-info/licenses/LICENSE
converso_ai-1.0.7.dist-info/METADATA
converso_ai-1.0.7.dist-info/WHEEL
converso_ai-1.0.7.dist-info/top_level.txt
converso_ai-1.0.7.dist-info/RECORD
