Metadata-Version: 2.4
Name: converso-ai
Version: 1.0.7
Summary: Python client for Converso AI API
Author-email: Muhammad Gohar <mg03164525711@gmail.com>
License: MIT
Project-URL: Converso-AI_Telegarm-Channel, https://t.me/conversoai
Project-URL: Converso-AI_Telegarm-Group, https://t.me/conversoai_chat
Project-URL: Converso_AI-API_Docs, https://conversoai.stylefort.store
Project-URL: Repository, https://github.com/muhammadgohar-official/converso-ai-python-library
Requires-Python: >=3.7
License-File: LICENSE
Requires-Dist: requests>=2.20.0
Dynamic: license-file
